[{"first_name":"Dario","last_name":"Saric","gamecode":"2017111513","position":"F","min":"33:20","fgm_fga":"3-10","ftm_fta":"0-0","threepm_threepa":"1-7","plus_minus":"+1","offensive_rebound":"1","total_rebound":"6","assist":"0","block":"3","steal":"0","turnover":"0","personal_foul":"1","points":"7","player_link":"/nba/playerstats.asp?id=5323&team=20"},{"first_name":"Robert","last_name":"Covington","gamecode":"2017111513","position":"F","min":"29:45","fgm_fga":"5-9","ftm_fta":"0-0","threepm_threepa":"2-5","plus_minus":"+16","offensive_rebound":"0","total_rebound":"6","assist":"1","block":"1","steal":"0","turnover":"2","personal_foul":"4","points":"12","player_link":"/nba/playerstats.asp?id=5253&team=20"},{"first_name":"Joel","last_name":"Embiid","gamecode":"2017111513","position":"C","min":"34:29","fgm_fga":"14-20","ftm_fta":"16-19","threepm_threepa":"2-3","plus_minus":"+19","offensive_rebound":"2","total_rebound":"15","assist":"7","block":"7","steal":"0","turnover":"2","personal_foul":"4","points":"46","player_link":"/nba/playerstats.asp?id=5294&team=20"},{"first_name":"Ben","last_name":"Simmons","gamecode":"2017111513","position":"G","min":"39:06","fgm_fga":"8-13","ftm_fta":"2-4","threepm_threepa":"0-0","plus_minus":"+19","offensive_rebound":"3","total_rebound":"9","assist":"10","block":"1","steal":"5","turnover":"1","personal_foul":"1","points":"18","player_link":"/nba/playerstats.asp?id=5600&team=20"},{"first_name":"JJ","last_name":"Redick","gamecode":"2017111513","position":"G","min":"34:54","fgm_fga":"4-15","ftm_fta":"3-4","threepm_threepa":"0-8","plus_minus":"+3","offensive_rebound":"0","total_rebound":"8","assist":"5","block":"0","steal":"1","turnover":"2","personal_foul":"4","points":"11","player_link":"/nba/playerstats.asp?id=4139&team=20"},{"first_name":"Timothé","last_name":"Luwawu-Cabarrot","gamecode":"2017111513","position":"","min":"24:42","fgm_fga":"4-10","ftm_fta":"0-0","threepm_threepa":"1-6","plus_minus":"+1","offensive_rebound":"1","total_rebound":"3","assist":"0","block":"1","steal":"0","turnover":"2","personal_foul":"2","points":"9","player_link":"/nba/playerstats.asp?id=5655&team=20"},{"first_name":"T.J.","last_name":"McConnell","gamecode":"2017111513","position":"","min":"22:30","fgm_fga":"3-5","ftm_fta":"0-0","threepm_threepa":"1-1","plus_minus":"-8","offensive_rebound":"1","total_rebound":"4","assist":"4","block":"0","steal":"1","turnover":"5","personal_foul":"0","points":"7","player_link":"/nba/playerstats.asp?id=5582&team=20"},{"first_name":"Amir","last_name":"Johnson","gamecode":"2017111513","position":"","min":"9:00","fgm_fga":"0-0","ftm_fta":"0-0","threepm_threepa":"0-0","plus_minus":"-10","offensive_rebound":"0","total_rebound":"0","assist":"0","block":"1","steal":"0","turnover":"2","personal_foul":"1","points":"0","player_link":"/nba/playerstats.asp?id=3982&team=20"},{"first_name":"Justin","last_name":"Anderson","gamecode":"2017111513","position":"","min":"7:43","fgm_fga":"1-4","ftm_fta":"3-3","threepm_threepa":"0-2","plus_minus":"-8","offensive_rebound":"0","total_rebound":"0","assist":"0","block":"0","steal":"0","turnover":"0","personal_foul":"1","points":"5","player_link":"/nba/playerstats.asp?id=5481&team=20"},{"first_name":"Richaun","last_name":"Holmes","gamecode":"2017111513","position":"","min":"4:31","fgm_fga":"0-0","ftm_fta":"0-0","threepm_threepa":"0-0","plus_minus":"-3","offensive_rebound":"0","total_rebound":"1","assist":"0","block":"1","steal":"0","turnover":"0","personal_foul":"1","points":"0","player_link":"/nba/playerstats.asp?id=5497&team=20"},{"total":"away","gamecode":"2017111513","min":"240","fgm_fga":"42-86(.488)","ftm_fta":"24-30(.800)","threepm_threepa":"7-32(.219)","plus_minus":"-","offensive_rebound":"8","total_rebound":"52","assist":"27","block":"15","steal":"7","turnover":"16","personal_foul":"19","points":"115"},{"total":"away","gamecode":"2017111513","min":"Min","fgm_fga":"FGM-FGA","ftm_fta":"FTM-FTA","threepm_threepa":"3PM-3PA","plus_minus":"+/-","offensive_rebound":"OR","total_rebound":"Reb","assist":"A","block":"Blk","steal":"Stl","turnover":"TO","personal_foul":"PF","points":"Pts"},{"first_name":"Brandon","last_name":"Ingram","gamecode":"2017111513","position":"F","min":"39:47","fgm_fga":"11-18","ftm_fta":"4-5","threepm_threepa":"0-0","plus_minus":"-2","offensive_rebound":"4","total_rebound":"11","assist":"3","block":"2","steal":"0","turnover":"2","personal_foul":"4","points":"26","player_link":"/nba/playerstats.asp?id=5601&team=13"},{"first_name":"Kyle","last_name":"Kuzma","gamecode":"2017111513","position":"F","min":"30:47","fgm_fga":"9-18","ftm_fta":"5-6","threepm_threepa":"1-4","plus_minus":"-4","offensive_rebound":"4","total_rebound":"7","assist":"1","block":"0","steal":"0","turnover":"2","personal_foul":"2","points":"24","player_link":"/nba/playerstats.asp?id=5840&team=13"},{"first_name":"Brook","last_name":"Lopez","gamecode":"2017111513","position":"C","min":"15:54","fgm_fga":"3-12","ftm_fta":"2-2","threepm_threepa":"0-5","plus_minus":"-11","offensive_rebound":"1","total_rebound":"2","assist":"2","block":"0","steal":"0","turnover":"0","personal_foul":"3","points":"8","player_link":"/nba/playerstats.asp?id=4472&team=13"},{"first_name":"Kentavious","last_name":"Caldwell-Pope","gamecode":"2017111513","position":"G","min":"41:15","fgm_fga":"4-11","ftm_fta":"2-2","threepm_threepa":"2-8","plus_minus":"0","offensive_rebound":"0","total_rebound":"7","assist":"2","block":"2","steal":"1","turnover":"0","personal_foul":"1","points":"12","player_link":"/nba/playerstats.asp?id=5159&team=13"},{"first_name":"Lonzo","last_name":"Ball","gamecode":"2017111513","position":"G","min":"21:25","fgm_fga":"1-9","ftm_fta":"0-0","threepm_threepa":"0-6","plus_minus":"-18","offensive_rebound":"3","total_rebound":"5","assist":"2","block":"0","steal":"1","turnover":"2","personal_foul":"3","points":"2","player_link":"/nba/playerstats.asp?id=5764&team=13"},{"first_name":"Jordan","last_name":"Clarkson","gamecode":"2017111513","position":"","min":"31:40","fgm_fga":"8-21","ftm_fta":"4-4","threepm_threepa":"0-2","plus_minus":"+3","offensive_rebound":"3","total_rebound":"6","assist":"5","block":"0","steal":"2","turnover":"0","personal_foul":"1","points":"20","player_link":"/nba/playerstats.asp?id=5357&team=13"},{"first_name":"Julius","last_name":"Randle","gamecode":"2017111513","position":"","min":"29:40","fgm_fga":"2-12","ftm_fta":"4-6","threepm_threepa":"0-1","plus_minus":"+5","offensive_rebound":"3","total_rebound":"8","assist":"1","block":"0","steal":"1","turnover":"3","personal_foul":"6","points":"8","player_link":"/nba/playerstats.asp?id=5318&team=13"},{"first_name":"Andrew","last_name":"Bogut","gamecode":"2017111513","position":"","min":"19:39","fgm_fga":"3-5","ftm_fta":"0-0","threepm_threepa":"0-0","plus_minus":"-2","offensive_rebound":"4","total_rebound":"10","assist":"2","block":"2","steal":"1","turnover":"0","personal_foul":"2","points":"6","player_link":"/nba/playerstats.asp?id=3927&team=13"},{"first_name":"Corey","last_name":"Brewer","gamecode":"2017111513","position":"","min":"9:53","fgm_fga":"1-3","ftm_fta":"1-2","threepm_threepa":"0-1","plus_minus":"-1","offensive_rebound":"0","total_rebound":"1","assist":"0","block":"0","steal":"1","turnover":"0","personal_foul":"1","points":"3","player_link":"/nba/playerstats.asp?id=4285&team=13"},{"total":"home","gamecode":"2017111513","min":"240","fgm_fga":"42-109(.385)","ftm_fta":"22-27(.815)","threepm_threepa":"3-27(.111)","plus_minus":"-","offensive_rebound":"22","total_rebound":"57","assist":"18","block":"6","steal":"7","turnover":"9","personal_foul":"23","points":"109"}]